bank/__init__.py
bank/admin.py
bank/apps.py
bank/models.py
bank/tests.py
bank/views.py
bank/migrations/0001_initial.py
bank/migrations/__init__.py
country/__init__.py
country/admin.py
country/apps.py
country/models.py
country/tests.py
country/views.py
country/migrations/0001_initial.py
country/migrations/__init__.py
currency/__init__.py
currency/admin.py
currency/apps.py
currency/models.py
currency/tests.py
currency/views.py
currency/migrations/0001_initial.py
currency/migrations/__init__.py
django_bank_utils-0.0.3.dist-info/LICENSE
django_bank_utils-0.0.3.dist-info/METADATA
django_bank_utils-0.0.3.dist-info/WHEEL
django_bank_utils-0.0.3.dist-info/top_level.txt
django_bank_utils-0.0.3.dist-info/RECORD
